statusbar/__init__.py
statusbar-0.1.22.dist-info/DESCRIPTION.rst
statusbar-0.1.22.dist-info/METADATA
statusbar-0.1.22.dist-info/RECORD
statusbar-0.1.22.dist-info/WHEEL
statusbar-0.1.22.dist-info/metadata.json
statusbar-0.1.22.dist-info/top_level.txt
tests/__init__.py
