Metadata-Version: 2.0
Name: statusbar
Version: 0.1.22
Summary: Module for displaying (text based) status update lines.
Home-page: https://github.com/mailund/statusbar
Author: Thomas Mailund
Author-email: mailund@birc.au.dk
License: GPLv3
Keywords: CLI status output
Platform: UNKNOWN
Classifier: Development Status :: 4 - Beta
Classifier: Environment :: Console
Classifier: Topic :: Utilities
Classifier: License :: OSI Approved :: GNU General Public License v3 or later (GPLv3+)
Classifier: Programming Language :: Python
Requires-Dist: termcolor (>=1.1.0)
